<?xml version='1.0' encoding='UTF-8'?>
<faces-config version="2.2"
              xmlns="http://xmlns.jcp.org/xml/ns/javaee"
              xmlns:xsi="http://www.w3.org/2001/XMLSchema-instance"
              xsi:schemaLocation="http://xmlns.jcp.org/xml/ns/javaee http://xmlns.jcp.org/xml/ns/javaee/web-facesconfig_2_2.xsd">
    <navigation-rule>
        <from-view-id>/index.xhtml</from-view-id>
        <navigation-case>
            <from-outcome>register</from-outcome>
            <to-view-id>/register.xhtml</to-view-id>
            <redirect/>
        </navigation-case>
        <navigation-case>
            <from-outcome>admin</from-outcome>
            <to-view-id>/adminView/mainPagesOfAdmin.xhtml</to-view-id>
            <redirect/>
        </navigation-case>
        <navigation-case>
            <from-outcome>client</from-outcome>
            <to-view-id>/clientView/mainPagesOfClient.xhtml</to-view-id>
            <redirect/>
        </navigation-case>
        <navigation-case>
            <from-outcome>trainer</from-outcome>
            <to-view-id>/trainerView/mainPagesOfTrainer.xhtml</to-view-id>
            <redirect/>
        </navigation-case>
    </navigation-rule>
    <navigation-rule>
        <from-view-id>/register.xhtml</from-view-id>
        <navigation-case>
            <from-outcome>index</from-outcome>
            <to-view-id>/index.xhtml</to-view-id>
            <redirect/>
        </navigation-case>
    </navigation-rule>
    <navigation-rule>
        <from-view-id>/adminView/mainPagesOfAdmin.xhtml</from-view-id>
        <navigation-case>
            <from-outcome>createUser</from-outcome>
            <to-view-id>/adminView/createNewUser.xhtml</to-view-id>
            <redirect/>
        </navigation-case>
        <navigation-case>
            <from-outcome>deleteUser</from-outcome>
            <to-view-id>/adminView/deleteUser.xhtml</to-view-id>
            <redirect/>
        </navigation-case>
        <navigation-case>
            <from-outcome>editRole</from-outcome>
            <to-view-id>/adminView/editRole.xhtml</to-view-id>
            <redirect/>
        </navigation-case>
        <navigation-case>
            <from-outcome>index</from-outcome>
            <to-view-id>/index.xhtml</to-view-id>
            <redirect/>
        </navigation-case>
    </navigation-rule>
    <navigation-rule>
        <from-view-id>/adminView/deleteUser.xhtml</from-view-id>
        <navigation-case>
            <from-outcome>admin</from-outcome>
            <to-view-id>/adminView/mainPagesOfAdmin.xhtml</to-view-id>
            <redirect/>
        </navigation-case>
    </navigation-rule>
    <navigation-rule>
        <from-view-id>/adminView/editRole.xhtml</from-view-id>
        <navigation-case>
            <from-outcome>admin</from-outcome>
            <to-view-id>/adminView/mainPagesOfAdmin.xhtml</to-view-id>
            <redirect/>
        </navigation-case>
    </navigation-rule>
    <navigation-rule>
        <from-view-id>/adminView/createNewUser.xhtml</from-view-id>
        <navigation-case>
            <from-outcome>admin</from-outcome>
            <to-view-id>/adminView/mainPagesOfAdmin.xhtml</to-view-id>
            <redirect/>
        </navigation-case>
    </navigation-rule>
    <navigation-rule>
        <from-view-id>/clientView/paySubscription.xhtml</from-view-id>
        <navigation-case>
            <from-outcome>client</from-outcome>
            <to-view-id>/clientView/mainPagesOfClient.xhtml</to-view-id>
            <redirect/>
        </navigation-case>
    </navigation-rule>
    <navigation-rule>
        <from-view-id>/clientView/createNewSubscription.xhtml</from-view-id>
        <navigation-case>
            <from-outcome>client</from-outcome>
            <to-view-id>/clientView/mainPagesOfClient.xhtml</to-view-id>
            <redirect/>
        </navigation-case>
    </navigation-rule>
    <navigation-rule>
        <from-view-id>/clientView/editDataYourself.xhtml</from-view-id>
        <navigation-case>
            <from-outcome>client</from-outcome>
            <to-view-id>/clientView/mainPagesOfClient.xhtml</to-view-id>
            <redirect/>
        </navigation-case>
    </navigation-rule>
    <navigation-rule>
        <from-view-id>/clientView/aboutSubscription.xhtml</from-view-id>
        <navigation-case>
            <from-outcome>client</from-outcome>
            <to-view-id>/clientView/mainPagesOfClient.xhtml</to-view-id>
            <redirect/>
        </navigation-case>
    </navigation-rule>
    <navigation-rule>
        <from-view-id>/clientView/deleteSubscription.xhtml</from-view-id>
        <navigation-case>
            <from-outcome>client</from-outcome>
            <to-view-id>/clientView/mainPagesOfClient.xhtml</to-view-id>
            <redirect/>
        </navigation-case>
    </navigation-rule>
    <navigation-rule>
        <from-view-id>/clientView/mainPagesOfClient.xhtml</from-view-id>
        <navigation-case>
            <from-outcome>paySub</from-outcome>
            <to-view-id>/clientView/paySubscription.xhtml</to-view-id>
            <redirect/>
        </navigation-case>
        <navigation-case>
            <from-outcome>createSub</from-outcome>
            <to-view-id>/clientView/createNewSubscription.xhtml</to-view-id>
            <redirect/>
        </navigation-case>
        <navigation-case>
            <from-outcome>deleteSub</from-outcome>
            <to-view-id>/clientView/deleteSubscription.xhtml</to-view-id>
            <redirect/>
        </navigation-case>
        <navigation-case>
            <from-outcome>update</from-outcome>
            <to-view-id>/clientView/editDataYourself.xhtml</to-view-id>
            <redirect/>
        </navigation-case>
        <navigation-case>
            <from-outcome>aboutSub</from-outcome>
            <to-view-id>/clientView/aboutSubscription.xhtml</to-view-id>
            <redirect/>
        </navigation-case>
        <navigation-case>
            <from-outcome>index</from-outcome>
            <to-view-id>/index.xhtml</to-view-id>
            <redirect/>
        </navigation-case>
    </navigation-rule>
    <navigation-rule>
        <from-view-id>/trainerView/mainPagesOfTrainer.xhtml</from-view-id>
        <navigation-case>
            <from-outcome>index</from-outcome>
            <to-view-id>/index.xhtml</to-view-id>
            <redirect/>
        </navigation-case>
        <navigation-case>
            <from-outcome>deleteGroup</from-outcome>
            <to-view-id>/trainerView/deleteGroup.xhtml</to-view-id>
            <redirect/>
        </navigation-case>
        <navigation-case>
            <from-outcome>createGroup</from-outcome>
            <to-view-id>/trainerView/createNewGroup.xhtml</to-view-id>
            <redirect/>
        </navigation-case>
        <navigation-case>
            <from-outcome>showFramedSub</from-outcome>
            <to-view-id>/trainerView/showFramedSubscription.xhtml</to-view-id>
            <redirect/>
        </navigation-case>
        <navigation-case>
            <from-outcome>listFrozen</from-outcome>
            <to-view-id>/trainerView/listFrozenClient.xhtml</to-view-id>
            <redirect/>
        </navigation-case>
        <navigation-case>
            <from-outcome>detailsGroup</from-outcome>
            <to-view-id>/trainerView/detailsGroup.xhtml</to-view-id>
            <redirect/>
        </navigation-case>
        <navigation-case>
            <from-outcome>editGroup</from-outcome>
            <to-view-id>/trainerView/editGroup.xhtml</to-view-id>
            <redirect/>
        </navigation-case>
    </navigation-rule>
    <navigation-rule>
        <from-view-id>/trainerView/editGroup.xhtml</from-view-id>
        <navigation-case>
            <from-outcome>trainer</from-outcome>
            <to-view-id>/trainerView/mainPagesOfTrainer.xhtml</to-view-id>
            <redirect/>
        </navigation-case>
    </navigation-rule>
    <navigation-rule>
        <from-view-id>/trainerView/detailsGroup.xhtml</from-view-id>
        <navigation-case>
            <from-outcome>trainer</from-outcome>
            <to-view-id>/trainerView/mainPagesOfTrainer.xhtml</to-view-id>
            <redirect/>
        </navigation-case>
    </navigation-rule>
    <navigation-rule>
        <from-view-id>/trainerView/listFrozenClient.xhtml</from-view-id>
        <navigation-case>
            <from-outcome>trainer</from-outcome>
            <to-view-id>/trainerView/mainPagesOfTrainer.xhtml</to-view-id>
            <redirect/>
        </navigation-case>
        <navigation-case>
            <from-outcome>changeGroup</from-outcome>
            <to-view-id>/trainerView/changeGroupToClient.xhtml</to-view-id>
            <redirect/>
        </navigation-case>
    </navigation-rule>
    <navigation-rule>
        <from-view-id>/trainerView/showFramedSubscription.xhtml</from-view-id>
        <navigation-case>
            <from-outcome>trainer</from-outcome>
            <to-view-id>/trainerView/mainPagesOfTrainer.xhtml</to-view-id>
            <redirect/>
        </navigation-case>
    </navigation-rule>
    <navigation-rule>
        <from-view-id>/trainerView/createNewGroup.xhtml</from-view-id>
        <navigation-case>
            <from-outcome>trainer</from-outcome>
            <to-view-id>/trainerView/mainPagesOfTrainer.xhtml</to-view-id>
            <redirect/>
        </navigation-case>
    </navigation-rule>
    <navigation-rule>
        <from-view-id>/trainerView/deleteGroup.xhtml</from-view-id>
        <navigation-case>
            <from-outcome>trainer</from-outcome>
            <to-view-id>/trainerView/mainPagesOfTrainer.xhtml</to-view-id>
            <redirect/>
        </navigation-case>
    </navigation-rule>
    <navigation-rule>
        <from-view-id>/trainerView/changeGroupToClient.xhtml</from-view-id>
        <navigation-case>
            <from-outcome>listFrozen</from-outcome>
            <to-view-id>/trainerView/listFrozenClient.xhtml</to-view-id>
        </navigation-case>
    </navigation-rule>
</faces-config>
